candypi/__init__.py
candypi/core.py
candypi/server.py
tests/__init__.py
tests/test_core.py
candypi-0.1.0.dist-info/LICENSE
candypi-0.1.0.dist-info/METADATA
candypi-0.1.0.dist-info/WHEEL
candypi-0.1.0.dist-info/entry_points.txt
candypi-0.1.0.dist-info/top_level.txt
candypi-0.1.0.dist-info/RECORD
